opmatch
